dopt/__init__.py
dopt/client.py
dopt/core/__init__.py
dopt/core/api_error.py
dopt/core/client_wrapper.py
dopt/core/datetime_utils.py
dopt/core/jsonable_encoder.py
dopt/core/remove_none_from_dict.py
dopt/environment.py
dopt/errors/__init__.py
dopt/errors/bad_request_error.py
dopt/errors/internal_server_error.py
dopt/errors/not_found_error.py
dopt/errors/unauthorized_error.py
dopt/py.typed
dopt/resources/__init__.py
dopt/resources/blocks/__init__.py
dopt/resources/blocks/client.py
dopt/resources/flows/__init__.py
dopt/resources/flows/client.py
dopt/types/__init__.py
dopt/types/bad_request_error_response_body.py
dopt/types/block_transition_query_string.py
dopt/types/block_transition_request_body.py
dopt/types/block_transition_request_params.py
dopt/types/flow_intent_query_string.py
dopt/types/flow_intent_query_string_tag.py
dopt/types/flow_intent_request_body.py
dopt/types/flow_intent_request_params.py
dopt/types/flow_intent_request_params_intent.py
dopt/types/get_block_query_string.py
dopt/types/get_block_request_params.py
dopt/types/get_block_response.py
dopt/types/get_block_response_fields_item.py
dopt/types/get_block_response_fields_item_boolean.py
dopt/types/get_block_response_fields_item_number.py
dopt/types/get_block_response_fields_item_rich_text.py
dopt/types/get_block_response_fields_item_string.py
dopt/types/get_block_response_state.py
dopt/types/get_block_response_type.py
dopt/types/get_flow_query_string.py
dopt/types/get_flow_query_string_tag.py
dopt/types/get_flow_request_params.py
dopt/types/get_flow_request_tag.py
dopt/types/get_flow_response.py
dopt/types/get_flow_response_blocks_item.py
dopt/types/get_flow_response_blocks_item_fields_item.py
dopt/types/get_flow_response_blocks_item_fields_item_boolean.py
dopt/types/get_flow_response_blocks_item_fields_item_number.py
dopt/types/get_flow_response_blocks_item_fields_item_rich_text.py
dopt/types/get_flow_response_blocks_item_fields_item_string.py
dopt/types/get_flow_response_blocks_item_state.py
dopt_blocks_python_client-1.0.28.dist-info/METADATA
dopt_blocks_python_client-1.0.28.dist-info/WHEEL
dopt_blocks_python_client-1.0.28.dist-info/RECORD
